loadingstuff/__init__.py
loadingstuff-1.0.1.dist-info/METADATA
loadingstuff-1.0.1.dist-info/WHEEL
loadingstuff-1.0.1.dist-info/top_level.txt
loadingstuff-1.0.1.dist-info/RECORD
