Metadata-Version: 2.1
Name: loadingstuff
Version: 1.0.1
Summary: loading bars & spinners
Home-page: UNKNOWN
Author: Kellan Butler
Author-email: kellanubutler52@gmail.com
License: UNKNOWN
Keywords: loading
Platform: UNKNOWN
Classifier: Development Status :: 4 - Beta
Classifier: Intended Audience :: Developers
Classifier: Programming Language :: Python :: 3
Classifier: Operating System :: POSIX :: Linux
